xero_mcp/__init__.py
xero_mcp/app.py
xero_mcp/auth_success.html
xero_mcp/cli.py
xero_mcp-0.1.10.dist-info/METADATA
xero_mcp-0.1.10.dist-info/WHEEL
xero_mcp-0.1.10.dist-info/entry_points.txt
xero_mcp-0.1.10.dist-info/top_level.txt
xero_mcp-0.1.10.dist-info/RECORD
