Metadata-Version: 2.2
Name: xero-mcp
Version: 0.1.10
Summary: Xero MCP Server
Requires-Python: >=3.10
Requires-Dist: aiohttp>=3.11.11
Requires-Dist: python-dotenv>=1.0.1
Requires-Dist: xero-python>=1.25.0
Requires-Dist: authlib>=1.3.0
Requires-Dist: requests>=2.32.3
Requires-Dist: click>=8.1.8
Requires-Dist: mcp[cli]>=1.3.0
